lpminimk3/__init__.py
lpminimk3/__version__.py
lpminimk3/_logging.py
lpminimk3/components.py
lpminimk3/device.py
lpminimk3/match.py
lpminimk3/midi_messages.py
lpminimk3/region.py
lpminimk3/system_midi_port_parser.py
lpminimk3/utils.py
lpminimk3/colors/__init__.py
lpminimk3/colors/_colors.py
lpminimk3/colors/web_color.py
lpminimk3/colors/web_colors.json
lpminimk3/colors/web_colors.schema.json
lpminimk3/examples/__init__.py
lpminimk3/examples/display_character.py
lpminimk3/examples/flash.py
lpminimk3/examples/hello.py
lpminimk3/examples/light_on_push.py
lpminimk3/examples/logos.py
lpminimk3/examples/party.py
lpminimk3/examples/print_text_scroll.py
lpminimk3/examples/sync_client.py
lpminimk3/examples/text_scroll_region.py
lpminimk3/graphics/__init__.py
lpminimk3/graphics/_graphics.py
lpminimk3/graphics/_parser.py
lpminimk3/graphics/_renderable.py
lpminimk3/graphics/_renderer.py
lpminimk3/graphics/_utils.py
lpminimk3/graphics/art.py
lpminimk3/graphics/render.py
lpminimk3/graphics/sync.py
lpminimk3/graphics/bitmaps/alien.bitmap.json
lpminimk3/graphics/bitmaps/apple.bitmap.json
lpminimk3/graphics/bitmaps/apple_old.bitmap.json
lpminimk3/graphics/bitmaps/chair.bitmap.json
lpminimk3/graphics/bitmaps/critical.bitmap.json
lpminimk3/graphics/bitmaps/data.bitmap.json
lpminimk3/graphics/bitmaps/diagonal.bitmap.json
lpminimk3/graphics/bitmaps/duck.bitmap.json
lpminimk3/graphics/bitmaps/facebook.bitmap.json
lpminimk3/graphics/bitmaps/ghost.bitmap.json
lpminimk3/graphics/bitmaps/gmail.bitmap.json
lpminimk3/graphics/bitmaps/google.bitmap.json
lpminimk3/graphics/bitmaps/green_arrow.bitmap.json
lpminimk3/graphics/bitmaps/green_plus.bitmap.json
lpminimk3/graphics/bitmaps/happy_face.bitmap.json
lpminimk3/graphics/bitmaps/heart.bitmap.json
lpminimk3/graphics/bitmaps/house.bitmap.json
lpminimk3/graphics/bitmaps/information.bitmap.json
lpminimk3/graphics/bitmaps/itunes.bitmap.json
lpminimk3/graphics/bitmaps/ludo.bitmap.json
lpminimk3/graphics/bitmaps/pacman.bitmap.json
lpminimk3-0.6.4.dist-info/licenses/LICENSE
lpminimk3-0.6.4.dist-info/METADATA
lpminimk3-0.6.4.dist-info/WHEEL
lpminimk3-0.6.4.dist-info/top_level.txt
lpminimk3-0.6.4.dist-info/RECORD
