Metadata-Version: 2.4
Name: lpminimk3
Version: 0.6.4
Summary: Python API for the Novation Launchpad Mini MK3
Home-page: https://github.com/obeezzy/lpminimk3
Author: Chronic Coder
Author-email: efeoghene.obebeduo@gmail.com
License: MIT
Classifier: License :: OSI Approved :: MIT License
Classifier: Programming Language :: Python :: 3
Classifier: Programming Language :: Python :: 3.7
License-File: LICENSE
Requires-Dist: python-rtmidi
Requires-Dist: jsonschema
Requires-Dist: websockets
Dynamic: author
Dynamic: author-email
Dynamic: classifier
Dynamic: description
Dynamic: description-content-type
Dynamic: home-page
Dynamic: license
Dynamic: license-file
Dynamic: requires-dist
Dynamic: summary
